odoo/addons/edi_account_invoice_import/README.rst
odoo/addons/edi_account_invoice_import/__init__.py
odoo/addons/edi_account_invoice_import/__manifest__.py
odoo/addons/edi_account_invoice_import/components/__init__.py
odoo/addons/edi_account_invoice_import/components/process.py
odoo/addons/edi_account_invoice_import/i18n/edi_account_invoice_import.pot
odoo/addons/edi_account_invoice_import/i18n/es.po
odoo/addons/edi_account_invoice_import/i18n/it.po
odoo/addons/edi_account_invoice_import/readme/CONTRIBUTORS.rst
odoo/addons/edi_account_invoice_import/readme/DESCRIPTION.rst
odoo/addons/edi_account_invoice_import/static/description/icon.png
odoo/addons/edi_account_invoice_import/static/description/index.html
odoo/addons/edi_account_invoice_import/templates/exchange_chatter_msg.xml
odoo/addons/edi_account_invoice_import/tests/__init__.py
odoo/addons/edi_account_invoice_import/tests/test_process.py
odoo14_addon_edi_account_invoice_import-14.0.1.1.1.dev6.dist-info/METADATA
odoo14_addon_edi_account_invoice_import-14.0.1.1.1.dev6.dist-info/WHEEL
odoo14_addon_edi_account_invoice_import-14.0.1.1.1.dev6.dist-info/top_level.txt
odoo14_addon_edi_account_invoice_import-14.0.1.1.1.dev6.dist-info/RECORD
