Metadata-Version: 2.1
Name: odoo14-addon-edi_account_invoice_import
Version: 14.0.1.1.1.dev6
Summary: Plug account_invoice_import into EDI machinery.
Home-page: https://github.com/OCA/edi
Author: ForgeFlow,Odoo Community Association (OCA)
Author-email: support@odoo-community.org
License: AGPL-3
Classifier: Programming Language :: Python
Classifier: Framework :: Odoo
Classifier: Framework :: Odoo :: 14.0
Classifier: License :: OSI Approved :: GNU Affero General Public License v3
Classifier: Development Status :: 3 - Alpha
Requires-Python: >=3.6
Requires-Dist: odoo14-addon-account-invoice-import
Requires-Dist: odoo14-addon-edi-oca
Requires-Dist: odoo<14.1dev,>=14.0a
